[{"id":1,"name":"snickerdoodle","body":"dsaf","ctime":1624896198},{"id":2,"name":"匿名希望","body":"これはどう？","ctime":1625069493},{"id":3,"name":"匿名希望","body":"いけてる","ctime":1625069503},{"id":4,"name":" ","body":"asd","ctime":1625388937},{"id":5,"name":"snickerdoodle","body":"aiueo","ctime":1625566626},{"id":6,"name":"N3onG","body":"sadfdsaf","ctime":1625566630},{"id":7,"name":"4n0nym0u5","body":"","ctime":1625575957},{"id":8,"name":"4n0nym0u5","body":"","ctime":1625575958},{"id":9,"name":"snickerdoodle","body":"できた","ctime":1625684839},{"id":10,"name":"snickerdoodle","body":"sadfdsaf","ctime":1625684847},{"id":11,"name":"4n0nym0u5","body":"","ctime":1625684849}]